opennews/__init__.py
opennews/fetch.py
opennews/getnews.py
opennews/models.py
opennews/parse.py
opennews/rss.txt
opennews-0.1.1.dist-info/LICENSE
opennews-0.1.1.dist-info/WHEEL
opennews-0.1.1.dist-info/METADATA
opennews-0.1.1.dist-info/RECORD
